snowypushy/__init__.py
snowypushy/common/__init__.py
snowypushy/common/type.py
snowypushy/features/__init__.py
snowypushy/features/connect.py
snowypushy/features/domo.py
snowypushy/features/hvac.py
snowypushy/features/snowflake.py
snowypushy/settings/__init__.py
snowypushy/tests/__init__.py
snowypushy/tests/test_config.py
snowypushy-0.4.3.dist-info/LICENSE
snowypushy-0.4.3.dist-info/METADATA
snowypushy-0.4.3.dist-info/WHEEL
snowypushy-0.4.3.dist-info/top_level.txt
snowypushy-0.4.3.dist-info/RECORD
