Metadata-Version: 2.1
Name: snowypushy
Version: 0.4.3
Summary: Snowy helps us download and upload data across various data sources (e.g. Snowflake, Oracle, SAP Hana and Domo).
Home-page: https://github.com/belsonheng/snowypushy
Author: Belson Heng
Author-email: belsonheng@hotmail.com
License: MIT
Download-URL: https://github.com/belsonheng/snowypushy/archive/v0.4.3.tar.gz
Keywords: data,migration,snowflake,domo
Platform: UNKNOWN
Classifier: Intended Audience :: Developers
Classifier: License :: OSI Approved :: MIT License
Classifier: Operating System :: OS Independent
Classifier: Programming Language :: Python :: 3
Requires-Dist: hvac (==0.9.6)
Requires-Dist: cryptography (==2.8)
Requires-Dist: mock (==2.0)
Requires-Dist: cffi (==1.13)
Requires-Dist: cx-Oracle (==7.0.0)
Requires-Dist: snowflake-sqlalchemy (==1.2.0)
Requires-Dist: SQLAlchemy (==1.3.7)
Requires-Dist: pandas (==0.25.1)
Requires-Dist: numpy (==1.16.4)
Requires-Dist: PyYAML (>=5.1.2)
Requires-Dist: pydomo (==0.2.3)
Requires-Dist: tqdm (==4.36.1)
Requires-Dist: idna (==2.8)
